admin_resumable2/__init__.py
admin_resumable2/fields.py
admin_resumable2/files.py
admin_resumable2/tests.py
admin_resumable2/urls.py
admin_resumable2/views.py
admin_resumable2/static/admin_resumable2/js/resumable.js
admin_resumable2/templates/admin_resumable2/file_input.html
resumable2-0.1.dist-info/LICENSE
resumable2-0.1.dist-info/METADATA
resumable2-0.1.dist-info/WHEEL
resumable2-0.1.dist-info/top_level.txt
resumable2-0.1.dist-info/RECORD
